territory/.__init__.py.un~
territory/.cli.py.un~
territory/.go.py.un~
territory/.python.py.un~
territory/__init__.py
territory/__main__.py
territory/api_client.py
territory/c.py
territory/cli.py
territory/files.py
territory/git.py
territory/go.py
territory/python.py
territory-1.5.1.dist-info/entry_points.txt
territory-1.5.1.dist-info/WHEEL
territory-1.5.1.dist-info/METADATA
territory-1.5.1.dist-info/RECORD
